anqa/events/__init__.py
anqa/events/__main__.py
anqa/events/_version.py
anqa/events/asyncapi/__init__.py
anqa/events/asyncapi/generator.py
anqa/events/asyncapi/models.py
anqa/events/asyncapi/registry.py
anqa/events/broker.py
anqa/events/brokers/__init__.py
anqa/events/brokers/kafka/__init__.py
anqa/events/brokers/kafka/broker.py
anqa/events/brokers/nats/__init__.py
anqa/events/brokers/nats/broker.py
anqa/events/brokers/nats/middlewares.py
anqa/events/brokers/pubsub/__init__.py
anqa/events/brokers/pubsub/broker.py
anqa/events/brokers/pubsub/settings.py
anqa/events/brokers/rabbitmq/__init__.py
anqa/events/brokers/rabbitmq/broker.py
anqa/events/brokers/rabbitmq/middlewares.py
anqa/events/brokers/redis/__init__.py
anqa/events/brokers/redis/broker.py
anqa/events/brokers/redis/middlewares.py
anqa/events/brokers/stub/__init__.py
anqa/events/brokers/stub/broker.py
anqa/events/brokers/stub/middlewares.py
anqa/events/cli.py
anqa/events/consumer.py
anqa/events/context.py
anqa/events/encoders/__init__.py
anqa/events/encoders/json.py
anqa/events/encoders/msgpack.py
anqa/events/encoders/pickle.py
anqa/events/exceptions.py
anqa/events/message.py
anqa/events/middleware.py
anqa/events/middlewares/__init__.py
anqa/events/middlewares/debug.py
anqa/events/middlewares/error.py
anqa/events/middlewares/healthcheck.py
anqa/events/middlewares/prometheus.py
anqa/events/middlewares/result.py
anqa/events/middlewares/retries.py
anqa/events/models.py
anqa/events/py.typed
anqa/events/service.py
anqa/events/settings.py
anqa/events/types.py
anqa_events-0.0.1.dist-info/METADATA
anqa_events-0.0.1.dist-info/WHEEL
anqa_events-0.0.1.dist-info/entry_points.txt
anqa_events-0.0.1.dist-info/RECORD
